SPO_Plus_Training/SPOPlus.py
SPO_Plus_Training/__init__.py
SPO_Plus_Training/visualize_graph.py
SPO_Plus_Training-0.0.1.dist-info/LICENSE
SPO_Plus_Training-0.0.1.dist-info/METADATA
SPO_Plus_Training-0.0.1.dist-info/WHEEL
SPO_Plus_Training-0.0.1.dist-info/top_level.txt
SPO_Plus_Training-0.0.1.dist-info/RECORD
