Metadata-Version: 2.1
Name: SPO_Plus_Training
Version: 0.0.1
Summary: A sample test package
Home-page: https://github.com/1362136/SPO-Plus-Training-Package
Author: Krishna Kalathur
Author-email: krishna.kalathur@gmail.com
License: MIT
Platform: UNKNOWN
Requires-Python: >=3.8
License-File: LICENSE
